ipywui/__init__.py
ipywui/comps.py
ipywui/core.py
ipywui/components/Accordion.vue
ipywui/components/AccordionItem.vue
ipywui/components/AppLayout.vue
ipywui/components/Box.vue
ipywui/components/Button.vue
ipywui/components/Checkbox.vue
ipywui/components/Clipboard.vue
ipywui/components/Col.vue
ipywui/components/ColorPicker.vue
ipywui/components/Combobox.vue
ipywui/components/Controller.vue
ipywui/components/DatePicker.vue
ipywui/components/DateTimePicker.vue
ipywui/components/Dialog.vue
ipywui/components/Display.vue
ipywui/components/Dropdown.vue
ipywui/components/FileUpload.vue
ipywui/components/HBox.vue
ipywui/components/HtmlMath.vue
ipywui/components/Image.vue
ipywui/components/Input.vue
ipywui/components/InputNumber.vue
ipywui/components/Label.vue
ipywui/components/MarkdownViewer.vue
ipywui/components/Play.vue
ipywui/components/Progress.vue
ipywui/components/RadioButtons.vue
ipywui/components/Row.vue
ipywui/components/Select.vue
ipywui/components/SelectColors.vue
ipywui/components/SelectNumbers.vue
ipywui/components/SelectTags.vue
ipywui/components/Slider.vue
ipywui/components/Stack.vue
ipywui/components/StackItem.vue
ipywui/components/TabPane.vue
ipywui/components/Tabs.vue
ipywui/components/TimePicker.vue
ipywui/components/ToggleButton.vue
ipywui/components/ToggleButtons.vue
ipywui/components/VBox.vue
ipywui/components/Valid.vue
ipywui/components/_Stub.vue
ipywui/widgets/__init__.py
ipywui/widgets/assets/css/md_code_highlight.css
ipywui/widgets/custom/clipboard/__init__.py
ipywui/widgets/custom/clipboard/index.css
ipywui/widgets/custom/clipboard/index.js
ipywui/widgets/custom/dialog/__init__.py
ipywui/widgets/custom/dialog/index.css
ipywui/widgets/custom/dialog/index.js
ipywui/widgets/custom/message/__init__.py
ipywui/widgets/custom/message/index.css
ipywui/widgets/custom/message/index.js
vuepy/__init__.py
vuepy/__main__.py
vuepy/log.py
vuepy/version.py
vuepy/cli/__init__.py
vuepy/cli/create_vue.py
vuepy/cli/template_vue/App.vue
vuepy/cli/template_vue/app.ipynb
org.vuepy.core-0.1.8.dist-info/LICENSE
org.vuepy.core-0.1.8.dist-info/METADATA
org.vuepy.core-0.1.8.dist-info/WHEEL
org.vuepy.core-0.1.8.dist-info/entry_points.txt
org.vuepy.core-0.1.8.dist-info/top_level.txt
org.vuepy.core-0.1.8.dist-info/RECORD
