Metadata-Version: 2.1
Name: org.vuepy.core
Version: 0.1.8
Summary: Vue.py is a progressive, incrementally-adoptable Python framework for building UI on the Jupyter Notebook.
Home-page: https://www.vuepy.org
Author: vuepy.org
Author-email: leilux.dev@gmail.com
License: MIT
Keywords: vue,Web UI,MVVM
Classifier: License :: OSI Approved :: MIT License
Classifier: Programming Language :: Python :: 3.7
Requires-Python: >=3.7
License-File: LICENSE
Requires-Dist: ipywidgets
Requires-Dist: markdown
Requires-Dist: anywidget
